README.rst
setup.cfg
setup.py
awsarchive/__init__.py
awsarchive.egg-info/PKG-INFO
awsarchive.egg-info/SOURCES.txt
awsarchive.egg-info/dependency_links.txt
awsarchive.egg-info/entry_points.txt
awsarchive.egg-info/requires.txt
awsarchive.egg-info/top_level.txt