Metadata-Version: 1.1
Name: awsarchive
Version: 0.1.0
Summary: Toolkit for archiving files using AWS products.
Home-page: https://github.com/billyshambrook/awsarchive
Author: Billy Shambrook
Author-email: billy.shambrook@gmail.com
License: MIT
Download-URL: https://github.com/billyshambrook/awsarchive/tarball/0.1.0
Keywords: aws glacier s3 backup archive sqs
Platform: UNKNOWN
